uparma/__init__.py
uparma/uparma.py
uparma/version.txt
uparma_py-0.1.0.dist-info/METADATA
uparma_py-0.1.0.dist-info/WHEEL
uparma_py-0.1.0.dist-info/top_level.txt
uparma_py-0.1.0.dist-info/RECORD
